{"index": 8, "timestamp": 1526915068.928679, "prev_hash": "b72a608760757800d536dc2fb533ff62669df7bebdb9c6704c366e2b5952fe89", "transactions": [{"tx_id": "1462c0d1-84f2-39f1-b4cd-cd25629ee1b3", "user_id": "e24ac7ba-a31c-3721-85fc-8f99813afbb1", "timestamp": "1526889405.719607", "science_data_id_list": "", "conference_data_id_list": "1549", "journal_data_id_list": "", "patent_data_id_list": "29,31,41,104", "action": "check", "reviewer": "", "first_title": "????????", "second_title": "?????", "data_type": "??,??"}, {"tx_id": "42ae91d7-aed6-3825-80d8-9cef314617d3", "user_id": "2b316fd2-1500-3f39-a8db-a786f789e04b", "timestamp": "1526889519.720123", "science_data_id_list": "", "conference_data_id_list": "1282,1284,1293,1290,1292,1245", "journal_data_id_list": "", "patent_data_id_list": "", "action": "check", "reviewer": "", "first_title": "????????", "second_title": "???", "data_type": "??"}, {"tx_id": "53c7c497-ff00-33af-916d-c1d1f2eee7bd", "user_id": "2b316fd2-1500-3f39-a8db-a786f789e04b", "timestamp": "1526889645.720617", "science_data_id_list": "", "conference_data_id_list": "1357,1596,1606", "journal_data_id_list": "xbyy-g201704019,xbyy-g201704016", "patent_data_id_list": "", "action": "check", "reviewer": "", "first_title": "????????", "second_title": "????", "data_type": "??,??"}, {"tx_id": "fcb1326d-1476-3ae7-b4e8-b50d5bc5a035", "user_id": "e24ac7ba-a31c-3721-85fc-8f99813afbb1", "timestamp": "1526889747.721079", "science_data_id_list": "", "conference_data_id_list": "2005", "journal_data_id_list": "hebsfdxzrkxxb200903026", "patent_data_id_list": "61,79", "action": "check", "reviewer": "", "first_title": "????????", "second_title": "????", "data_type": "??,??,??"}, {"tx_id": "bfaa0602-2ec5-3a1e-a667-25d2608ca0b7", "user_id": "e24ac7ba-a31c-3721-85fc-8f99813afbb1", "timestamp": "1526889872.721565", "science_data_id_list": "", "conference_data_id_list": "", "journal_data_id_list": "", "patent_data_id_list": "11,15,21,29", "action": "check", "reviewer": "", "first_title": "????????", "second_title": "?????", "data_type": "??"}, {"tx_id": "ed097811-4cc5-3f57-8b01-6847bd277a73", "user_id": "2a528fad-f1db-3c5c-8ee0-cadd46f53492", "timestamp": "1526889994.722037", "science_data_id_list": "", "conference_data_id_list": "2143", "journal_data_id_list": "kjzxdb200926117,kjxx200926466,kjqbkfyjj200922035", "patent_data_id_list": "179", "action": "check", "reviewer": "", "first_title": "????????", "second_title": "???", "data_type": "??,??,??"}], "nonce": 3984031}